antchain_sdk_ak_7257696016e54ac8a1e0ed2d532c3c09/__init__.py
antchain_sdk_ak_7257696016e54ac8a1e0ed2d532c3c09/client.py
antchain_sdk_ak_7257696016e54ac8a1e0ed2d532c3c09/models.py
antchain_ak_7257696016e54ac8a1e0ed2d532c3c09-1.0.1.dist-info/LICENSE
antchain_ak_7257696016e54ac8a1e0ed2d532c3c09-1.0.1.dist-info/METADATA
antchain_ak_7257696016e54ac8a1e0ed2d532c3c09-1.0.1.dist-info/WHEEL
antchain_ak_7257696016e54ac8a1e0ed2d532c3c09-1.0.1.dist-info/top_level.txt
antchain_ak_7257696016e54ac8a1e0ed2d532c3c09-1.0.1.dist-info/RECORD
